naive_text/__init__.py
naive_text/normalizer.py
naive_text/sentence.py
naive_text-0.0.1.dist-info/LICENSE
naive_text-0.0.1.dist-info/METADATA
naive_text-0.0.1.dist-info/WHEEL
naive_text-0.0.1.dist-info/top_level.txt
naive_text-0.0.1.dist-info/RECORD
