Metadata-Version: 2.1
Name: naive-text
Version: 0.0.1
Summary: Text utils in Python.
Home-page: https://github.com/naivenlp/naive-text
Author: ZhouYang Luo
Author-email: zhouyang.luo@gmail.com
License: Apache Software License
Platform: UNKNOWN
Classifier: Programming Language :: Python :: 3
Classifier: Programming Language :: Python :: 3.5
Classifier: Programming Language :: Python :: 3.6
Classifier: Programming Language :: Python :: 3.7
Classifier: Programming Language :: Python :: 3.8
Classifier: Programming Language :: Python :: 3.9
Classifier: License :: OSI Approved :: Apache Software License
Classifier: Operating System :: OS Independent
Classifier: Topic :: Scientific/Engineering :: Artificial Intelligence
Requires-Dist: opencc-python-reimplemented
